Metadata-Version: 2.2
Name: flavius-py310
Version: 0.2.0
Summary: A Python client for Flavius
Author: Kasma, Inc.
Keywords: flavius,graph,database
Classifier: Development Status :: 4 - Beta
Classifier: Intended Audience :: Developers
Classifier: License :: OSI Approved :: Apache Software License
Classifier: Operating System :: OS Independent
Classifier: Programming Language :: Python :: 3.10
Classifier: Programming Language :: Python :: 3.11
Classifier: Programming Language :: Python :: 3.12
Classifier: Topic :: Database
Classifier: Topic :: Software Development
Requires-Dist: requests>=2.32.3
Requires-Dist: python-dateutil>=2.9.0.post0
Dynamic: author
Dynamic: classifier
Dynamic: description
Dynamic: description-content-type
Dynamic: keywords
Dynamic: requires-dist
Dynamic: summary
